{
  "configs": {
    "61754d71": {
      "template_id": "1f814897443847afbdc26c5fdea696e9.png",
      "font_id": null,
      "image_x": "45",
      "image_y": "55",
      "image_size": "36",
      "text_y": "80",
      "font_size": "5",
      "text_color": "a05a5a"
    },
    "46372d60": {
      "template_id": "1f814897443847afbdc26c5fdea696e9.png",
      "font_id": null,
      "image_x": 50,
      "image_y": 50,
      "image_size": 39,
      "text_y": 76,
      "font_size": 5,
      "text_color": "a05a5a"
    },
    "bec3fe2e": {
      "template_id": "1f814897443847afbdc26c5fdea696e9.png",
      "font_id": null,
      "conference_name": "Tech conf!",
      "share_message": "Join me at tech conf!",
      "image_x": 50,
      "image_y": 46,
      "image_size": 39,
      "image_shape": "circle",
      "text_x": 50,
      "text_y": 78,
      "font_size": 4,
      "text_color": "000aff"
    },
    "729c1382": {
      "template_id": "1f814897443847afbdc26c5fdea696e9.png",
      "font_id": null,
      "conference_name": "Tech conf!",
      "page_subtitle": "Generate your conference profile picturesssssss",
      "footer_text": "FFFFFFFF DFFGFHGHG sfgdngn",
      "share_message": "Join me at tech conf!",
      "image_x": 50,
      "image_y": 45,
      "image_size": 39,
      "image_shape": "circle",
      "text_x": 50,
      "text_y": 78,
      "font_size": 4,
      "text_color": "000aff"
    }
  },
  "default": {
    "template_id": "1f814897443847afbdc26c5fdea696e9.png",
    "font_id": null,
    "conference_name": "Tech conf!",
    "page_subtitle": "Generate your conference profile picturesssssss",
    "footer_text": "FFFFFFFF DFFGFHGHG sfgdngn",
    "share_message": "Join me at tech conf!",
    "image_x": 50,
    "image_y": 45,
    "image_size": 39,
    "image_shape": "circle",
    "text_x": 50,
    "text_y": 78,
    "font_size": 4,
    "text_color": "000aff"
  }
}